streamlit_quill/__init__.py
streamlit_quill/frontend/build/asset-manifest.json
streamlit_quill/frontend/build/bootstrap.min.css
streamlit_quill/frontend/build/index.html
streamlit_quill/frontend/build/precache-manifest.a50d802635e2faf06a7a12e184018d14.js
streamlit_quill/frontend/build/precache-manifest.d620fc52d24ce04bffee05b552ed2a5e.js
streamlit_quill/frontend/build/quill.bubble.css
streamlit_quill/frontend/build/quill.core.css
streamlit_quill/frontend/build/quill.snow.css
streamlit_quill/frontend/build/service-worker.js
streamlit_quill/frontend/build/style.css
streamlit_quill/frontend/build/static/js/2.aa4020dc.chunk.js
streamlit_quill/frontend/build/static/js/2.aa4020dc.chunk.js.LICENSE.txt
streamlit_quill/frontend/build/static/js/2.aa4020dc.chunk.js.map
streamlit_quill/frontend/build/static/js/main.4a02d5f2.chunk.js
streamlit_quill/frontend/build/static/js/main.4a02d5f2.chunk.js.map
streamlit_quill/frontend/build/static/js/main.c0d8a2c1.chunk.js
streamlit_quill/frontend/build/static/js/main.c0d8a2c1.chunk.js.map
streamlit_quill/frontend/build/static/js/runtime-main.11ec9aca.js
streamlit_quill/frontend/build/static/js/runtime-main.11ec9aca.js.map
streamlit_quill-0.0.2.dist-info/LICENSE
streamlit_quill-0.0.2.dist-info/METADATA
streamlit_quill-0.0.2.dist-info/WHEEL
streamlit_quill-0.0.2.dist-info/top_level.txt
streamlit_quill-0.0.2.dist-info/RECORD
